<annotation>
	<folder>balls_dataset</folder>
	<filename>WIN_20241028_16_57_46_Pro.jpg</filename>
	<path>C:\Users\Utente\Desktop\balls_dataset\WIN_20241028_16_57_46_Pro.jpg</path>
	<source>
		<database>Unknown</database>
	</source>
	<size>
		<width>1280</width>
		<height>720</height>
		<depth>3</depth>
	</size>
	<segmented>0</segmented>
	<object>
		<name>silver_ball</name>
		<pose>Unspecified</pose>
		<truncated>0</truncated>
		<difficult>0</difficult>
		<bndbox>
			<xmin>843</xmin>
			<ymin>232</ymin>
			<xmax>1113</xmax>
			<ymax>495</ymax>
		</bndbox>
	</object>
	<object>
		<name>black_ball</name>
		<pose>Unspecified</pose>
		<truncated>0</truncated>
		<difficult>0</difficult>
		<bndbox>
			<xmin>14</xmin>
			<ymin>157</ymin>
			<xmax>295</xmax>
			<ymax>453</ymax>
		</bndbox>
	</object>
</annotation>
